notioncalendarsync/__init__.py
notioncalendarsync/google_calendar.py
notioncalendarsync/notion_api.py
notioncalendarsync/test.py
dominicus88-1.1.0.dist-info/LICENSE
dominicus88-1.1.0.dist-info/METADATA
dominicus88-1.1.0.dist-info/WHEEL
dominicus88-1.1.0.dist-info/top_level.txt
dominicus88-1.1.0.dist-info/RECORD
