Metadata-Version: 2.1
Name: dominicus88
Version: 1.1.0
Summary: The unofficial Notion API extended with the option to sync your Notion events to Google Calendar.
Home-page: https://github.com/glowingkitty/Notion-Calendar-Sync
Author: Marco
License: UNKNOWN
Platform: UNKNOWN
Classifier: Programming Language :: Python :: 3
Classifier: License :: OSI Approved :: MIT License
Classifier: Operating System :: OS Independent
Requires-Python: >=3.6
Requires-Dist: notion
Requires-Dist: google-api-python-client
Requires-Dist: google-auth-httplib2
Requires-Dist: google-auth-oauthlib
